PyTlin.py
PyTlin-1.2.dist-info/DESCRIPTION.rst
PyTlin-1.2.dist-info/METADATA
PyTlin-1.2.dist-info/RECORD
PyTlin-1.2.dist-info/WHEEL
PyTlin-1.2.dist-info/metadata.json
PyTlin-1.2.dist-info/top_level.txt
