Metadata-Version: 2.0
Name: PyTlin
Version: 1.2
Summary: Kotlin functions also, let, and run, as well as sh-like (and Mathematica-like) piping syntax
Home-page: https://github.com/frejonb/PyTlin
Author: F. G. Rejon Barrera
Author-email: f.g.rejonbarrera@gmail.com
License: MIT
Platform: UNKNOWN
Classifier: Programming Language :: Python :: 3
Classifier: License :: OSI Approved :: MIT License
Classifier: Operating System :: OS Independent
